webtool
xmind2testcase_wzc
