Metadata-Version: 2.1
Name: xmind2testcase-wzc
Version: 1.7.0
Summary: xmind2testcase_wzc基于Python实现，提供了一个高效测试用例设计的解决方案！
Home-page: 
Author: Devin
Author-email: 
License: MIT
Keywords: xmind2testcase_wzc, testcase, test, testing, xmind, 思维导图, XMind思维导图
Classifier: Programming Language :: Python :: 3
Classifier: License :: OSI Approved :: MIT License
Classifier: Operating System :: OS Independent
Requires-Python: >=3.0, <4
License-File: LICENSE
Requires-Dist: xmind
Requires-Dist: flask
Requires-Dist: arrow
Requires-Dist: pandas
